extraction/__init__.py
extraction/extractor.py
extraction/qa_extractor.py
extraction/utils.py
extraction/bert_qa_extractor/__init__.py
extraction/bert_qa_extractor/bert_qa_extractor.py
cosmos_extraction-0.0.1.dist-info/LICENSE
cosmos_extraction-0.0.1.dist-info/METADATA
cosmos_extraction-0.0.1.dist-info/WHEEL
cosmos_extraction-0.0.1.dist-info/top_level.txt
cosmos_extraction-0.0.1.dist-info/RECORD
